fb_atm/__init__.py
fb_atm-0.1.8.2.dist-info/METADATA
fb_atm-0.1.8.2.dist-info/WHEEL
fb_atm-0.1.8.2.dist-info/entry_points.txt
fb_atm-0.1.8.2.dist-info/top_level.txt
fb_atm-0.1.8.2.dist-info/RECORD
