Metadata-Version: 2.1
Name: fb_atm
Version: 0.1.8.2
Summary: An application that informs you of the different modules and very easy to use.
Home-page: https://www.facebook.com/bk4human
Author: Mahdi Hasan Shuvo
Author-email: shvo.mex@gmail.com
License: MIT
Project-URL: GitHub, https://github.com/Shuvo-BBHH/
Project-URL: Bug Reports, https://www.facebook.com/bk4human
Project-URL: Source, https://github.com/Shuvo-BBHH/mahdix
Keywords: Shuvo-BBHH,MAHDI HASAN,Shuvo BBHH,Bk4kuman
Classifier: Programming Language :: Python :: 3
Classifier: License :: OSI Approved :: MIT License
Classifier: Operating System :: OS Independent
Requires-Python: >=3.11
Requires-Dist: click
Requires-Dist: pytz
